itertypes/__init__.py
itertypes/itertypes.py
itertypes/tests.py
itertypes-1.6.1.dist-info/LICENSE
itertypes-1.6.1.dist-info/METADATA
itertypes-1.6.1.dist-info/WHEEL
itertypes-1.6.1.dist-info/top_level.txt
itertypes-1.6.1.dist-info/RECORD
