Metadata-Version: 2.1
Name: itertypes
Version: 1.6.1
Summary: A small library used to obtain types for various builtin iterators.
Home-page: https://github.com/Kreusada/itertypes
Author: Kreusada
Author-email: kreusadaprojects@gmail.com
License: UNKNOWN
Platform: UNKNOWN
Classifier: Programming Language :: Python :: 3
Classifier: License :: OSI Approved :: MIT License
Classifier: Operating System :: OS Independent
License-File: LICENSE
